{
  "project_info": {
    "project_number": "322858170276",
    "project_id": "ichiraku-d9efd",
    "storage_bucket": "ichiraku-d9efd.appspot.com"
  },
  "client": [
    {
      "client_info": {
        "mobilesdk_app_id": "1:322858170276:android:acc117dc20aca7fabab331",
        "android_client_info": {
          "package_name": "com.example.testgeo"
        }
      },
      "oauth_client": [
        {
          "client_id": "322858170276-3kgpahqrma02bnmd0cpi4g0srae9kcjh.apps.googleusercontent.com",
          "client_type": 3
        }
      ],
      "api_key": [
        {
          "current_key": "AIzaSyDGRLphqAoNlPVkM-c3gkWf70JMyeFw_2c"
        }
      ],
      "services": {
        "appinvite_service": {
          "other_platform_oauth_client": [
            {
              "client_id": "322858170276-3kgpahqrma02bnmd0cpi4g0srae9kcjh.apps.googleusercontent.com",
              "client_type": 3
            }
          ]
        }
      }
    }
  ],
  "configuration_version": "1"
}